AnomalyDetector.py
setup.py
CSV_anomaly_detector.egg-info/PKG-INFO
CSV_anomaly_detector.egg-info/SOURCES.txt
CSV_anomaly_detector.egg-info/dependency_links.txt
CSV_anomaly_detector.egg-info/entry_points.txt
CSV_anomaly_detector.egg-info/requires.txt
CSV_anomaly_detector.egg-info/top_level.txt