Metadata-Version: 1.1
Name: CSV-anomaly-detector
Version: 1.2.16
Summary: A Python tool to detect Anamolies
Home-page: github.com/raj040492/CSV-anomaly-detector
Author: Rajkumar
Author-email: rajkumar.s@imaginea.com
License: MIT
Keywords: detect Anamolies in CSV files
Platform: UNKNOWN
Classifier: Development Status :: 4 - Beta
Classifier: Intended Audience :: Developers
Classifier: Topic :: Software Development :: Build Tools
Classifier: License :: OSI Approved :: MIT License
Classifier: Programming Language :: Python :: 2.7
